cv_io/__init__.py
cv_io/collection.py
cv_io/flowlib.py
cv_io/pfmutil.py
cv_io/sintel_io.py
cv_io-1.1.0.dist-info/LICENSE
cv_io-1.1.0.dist-info/METADATA
cv_io-1.1.0.dist-info/WHEEL
cv_io-1.1.0.dist-info/top_level.txt
cv_io-1.1.0.dist-info/RECORD
