Metadata-Version: 2.1
Name: cv-io
Version: 1.1.0
Summary: A collection of I/O scripts for computer vision formats.
Home-page: https://github.com/saeid-h/Computer-Vision-IO.git
Author: Saeid Hosseinipoor
Author-email: shossei1@stevens.edu
License: UNKNOWN
Platform: UNKNOWN
Classifier: Programming Language :: Python :: 3
Classifier: License :: OSI Approved :: MIT License
Classifier: Operating System :: OS Independent
Requires-Python: >=3.5
